{
  "indexes": [
    {
      "collectionGroup": "announcements",
      "queryScope": "COLLECTION",
      "fields": [
        {
          "fieldPath": "active",
          "order": "ASCENDING"
        },
        {
          "fieldPath": "createdAt",
          "order": "DESCENDING"
        }
      ]
    },
    {
      "collectionGroup": "messages",
      "queryScope": "COLLECTION",
      "fields": [
        {
          "fieldPath": "organizationId",
          "order": "ASCENDING"
        },
        {
          "fieldPath": "isAnnouncement",
          "order": "ASCENDING"
        },
        {
          "fieldPath": "__name__",
          "order": "ASCENDING"
        }
      ]
    }
  ],
  "fieldOverrides": []
}